passl/__init__.py
passl/datasets/__init__.py
passl/datasets/builder.py
passl/datasets/cifar.py
passl/datasets/folder.py
passl/datasets/imagenet.py
passl/datasets/textimagedataset.py
passl/datasets/preprocess/__init__.py
passl/datasets/preprocess/builder.py
passl/datasets/preprocess/cv2_func.py
passl/datasets/preprocess/cv2_trans.py
passl/datasets/preprocess/transforms.py
passl/engine/__init__.py
passl/engine/launch.py
passl/engine/trainer.py
passl/hooks/__init__.py
passl/hooks/builder.py
passl/hooks/checkpoint_hook.py
passl/hooks/clip_optimizer_hook.py
passl/hooks/evaluate_hook.py
passl/hooks/hook.py
passl/hooks/log_hook.py
passl/hooks/lr_scheduler_hook.py
passl/hooks/optimizer_hook.py
passl/hooks/timer_hook.py
passl/hooks/visual_hook.py
passl/modeling/__init__.py
passl/modeling/architectures/BYOL.py
passl/modeling/architectures/CLIPWrapper.py
passl/modeling/architectures/MoCoBYOL.py
passl/modeling/architectures/__init__.py
passl/modeling/architectures/builder.py
passl/modeling/architectures/byol_clas.py
passl/modeling/architectures/clas.py
passl/modeling/architectures/moco.py
passl/modeling/architectures/simclr.py
passl/modeling/backbones/__init__.py
passl/modeling/backbones/base_transformer.py
passl/modeling/backbones/builder.py
passl/modeling/backbones/clip.py
passl/modeling/backbones/resnet.py
passl/modeling/backbones/resnetcifar.py
passl/modeling/backbones/resnetimagenet.py
passl/modeling/backbones/resnetsimclr.py
passl/modeling/backbones/transformer.py
passl/modeling/backbones/vision_transformer.py
passl/modeling/heads/__init__.py
passl/modeling/heads/builder.py
passl/modeling/heads/clas_head.py
passl/modeling/heads/clip_head.py
passl/modeling/heads/contrastive_head.py
passl/modeling/heads/l2_head.py
passl/modeling/heads/mb_head.py
passl/modeling/heads/simclr_contrastive_head.py
passl/modeling/necks/__init__.py
passl/modeling/necks/base_neck.py
passl/modeling/necks/builder.py
passl/modules/__init__.py
passl/modules/ddp.py
passl/modules/freeze.py
passl-0.0.4.dist-info/LICENSE
passl-0.0.4.dist-info/METADATA
passl-0.0.4.dist-info/WHEEL
passl-0.0.4.dist-info/entry_points.txt
passl-0.0.4.dist-info/top_level.txt
passl-0.0.4.dist-info/RECORD
